OpenZerox/__init__.py
OpenZerox/openzerox.py
OpenZerox/utils.py
OpenZerox-0.1.20.dist-info/METADATA
OpenZerox-0.1.20.dist-info/WHEEL
OpenZerox-0.1.20.dist-info/top_level.txt
OpenZerox-0.1.20.dist-info/RECORD
